DSDP/__init__.py
DSDP/__main__.py
DSDP/binding_site_model.pth
DSDP/DSDP_blind_docking/DSDP_blind
DSDP/test_data/1a4i/1a4i_protein.pdbqt
DSDP/test_data/1a4i/1a4i_ligand.pdbqt
DSDP/test_data/1a2b/1a2b_ligand.pdbqt
DSDP/test_data/1a2b/1a2b_protein.pdbqt
DSDP/protein_feature_tool/17_FEATURES_DATA.txt
DSDP/protein_feature_tool/protein_feature_tool
DSDP/surface_tool/surface_tool
DSDP/DSDP_redocking/DSDP_redock
dsdp-1.0.dist-info/LICENSE
dsdp-1.0.dist-info/METADATA
dsdp-1.0.dist-info/WHEEL
dsdp-1.0.dist-info/entry_points.txt
dsdp-1.0.dist-info/RECORD
