Metadata-Version: 2.1
Name: dsdp
Version: 1.0
Summary: Python Wrapper for DSDP
Keywords: DSDP,molecular docking
Classifier: Development Status :: 5 - Production/Stable
Classifier: Environment :: GPU :: NVIDIA CUDA
Classifier: License :: OSI Approved :: Apache Software License
Classifier: Topic :: Scientific/Engineering :: Physics
Classifier: Topic :: Scientific/Engineering :: Chemistry
Classifier: Programming Language :: Python :: 3
Classifier: Operating System :: POSIX :: Linux
Requires-Dist: tqdm
Requires-Dist: scikit-image
